Metadata-Version: 2.1
Name: gym-handOfJustice
Version: 0.0.12
Summary: A openAI Gym Env for a Robotic arm that imitates an arm which would be given through a feed
Home-page: UNKNOWN
Author: UNKNOWN
Author-email: UNKNOWN
License: UNKNOWN
Platform: UNKNOWN
